chroma_mcp/__init__.py
chroma_mcp/__main__.py
chroma_mcp/app.py
chroma_mcp/cli.py
chroma_mcp/server.py
chroma_mcp/types.py
chroma_mcp/dev_scripts/__init__.py
chroma_mcp/dev_scripts/build.py
chroma_mcp/dev_scripts/project_root.py
chroma_mcp/dev_scripts/publish.py
chroma_mcp/dev_scripts/release.py
chroma_mcp/tools/__init__.py
chroma_mcp/tools/auto_log_chat_bridge.py
chroma_mcp/tools/collection_tools.py
chroma_mcp/tools/document_tools.py
chroma_mcp/tools/thinking_tools.py
chroma_mcp/utils/__init__.py
chroma_mcp/utils/chroma_client.py
chroma_mcp/utils/config.py
chroma_mcp/utils/errors.py
chroma_mcp_client/__init__.py
chroma_mcp_client/analysis.py
chroma_mcp_client/auto_log_chat_impl.py
chroma_mcp_client/cli.py
chroma_mcp_client/connection.py
chroma_mcp_client/context.py
chroma_mcp_client/deprecated_cli.py
chroma_mcp_client/indexing.py
chroma_mcp_client/interactive_promoter.py
chroma_mcp_client/learnings.py
chroma_mcp_client/pytest_plugin.py
chroma_mcp_client/query.py
chroma_mcp_client/scripts/__init__.py
chroma_mcp_client/scripts/analyze_chat.py
chroma_mcp_client/scripts/log_chat.py
chroma_mcp_client/scripts/log_error.py
chroma_mcp_client/scripts/log_quality.py
chroma_mcp_client/scripts/log_test.py
chroma_mcp_client/scripts/promote_learning.py
chroma_mcp_client/scripts/review_promote.py
chroma_mcp_client/scripts/validate_evidence.py
chroma_mcp_client/validation/__init__.py
chroma_mcp_client/validation/code_quality_collector.py
chroma_mcp_client/validation/evidence_collector.py
chroma_mcp_client/validation/promotion.py
chroma_mcp_client/validation/runtime_collector.py
chroma_mcp_client/validation/schemas.py
chroma_mcp_client/validation/test_collector.py
chroma_mcp_client/validation/test_workflow.py
chroma_mcp_thinking/__init__.py
chroma_mcp_thinking/thinking_cli.py
chroma_mcp_thinking/thinking_session.py
chroma_mcp_thinking/utils.py
chroma_mcp_server-0.2.27.dist-info/METADATA
chroma_mcp_server-0.2.27.dist-info/WHEEL
chroma_mcp_server-0.2.27.dist-info/entry_points.txt
chroma_mcp_server-0.2.27.dist-info/licenses/LICENSE.md
chroma_mcp_server-0.2.27.dist-info/RECORD
