Metadata-Version: 2.4
Name: chroma-mcp-server
Version: 0.2.27
Summary: Chroma MCP Server - Vector Database Integration for LLM Applications
Project-URL: Homepage, https://github.com/djm81/chroma_mcp_server
Project-URL: Repository, https://github.com/djm81/chroma_mcp_server.git
Project-URL: Documentation, https://github.com/djm81/chroma_mcp_server#readme
Author-email: Nold Coaching & Consulting <info@noldcoaching.de>
License-Expression: MIT
License-File: LICENSE.md
Keywords: chroma,embeddings,llm,mcp,vector-database
Classifier: Development Status :: 4 - Beta
Classifier: Intended Audience :: Developers
Classifier: License :: OSI Approved :: MIT License
Classifier: Programming Language :: Python :: 3
Classifier: Programming Language :: Python :: 3.10
Classifier: Programming Language :: Python :: 3.11
Classifier: Programming Language :: Python :: 3.12
Classifier: Topic :: Software Development :: Libraries :: Python Modules
Requires-Python: >=3.10
Requires-Dist: chromadb>=1.0.4
Requires-Dist: fastapi>=0.115.0
Requires-Dist: mcp>=1.6.0
Requires-Dist: numpy<2.0.0
Requires-Dist: onnxruntime>=1.21.0
Requires-Dist: pydantic>=2.11.3
Requires-Dist: python-dotenv>=1.1.0
Requires-Dist: sentence-transformers>=4.1.0
Requires-Dist: transformers~=4.41.0
Requires-Dist: uvicorn>=0.34.1
Provides-Extra: aimodels
Requires-Dist: boto3>=1.37.34; extra == 'aimodels'
Requires-Dist: cohere>=5.15.0; extra == 'aimodels'
Requires-Dist: google-generativeai>=0.8.4; extra == 'aimodels'
Requires-Dist: huggingface-hub>=0.30.2; extra == 'aimodels'
Requires-Dist: ollama>=0.4.7; extra == 'aimodels'
Requires-Dist: openai>=1.74.0; extra == 'aimodels'
Requires-Dist: voyageai>=0.3.2; extra == 'aimodels'
Provides-Extra: client
Requires-Dist: gitpython>=3.1.44; extra == 'client'
Provides-Extra: dev
Requires-Dist: black>=25.1.0; extra == 'dev'
Requires-Dist: isort>=6.0.1; extra == 'dev'
Requires-Dist: mypy>=1.15.0; extra == 'dev'
Requires-Dist: pylint>=3.3.6; extra == 'dev'
Requires-Dist: types-pyyaml>=6.0.12.20250402; extra == 'dev'
Provides-Extra: devtools
Requires-Dist: black>=25.1.0; extra == 'devtools'
Requires-Dist: isort>=6.0.1; extra == 'devtools'
Requires-Dist: mypy>=1.15.0; extra == 'devtools'
Requires-Dist: pylint>=3.3.6; extra == 'devtools'
Requires-Dist: types-pyyaml>=6.0.12.20250402; extra == 'devtools'
Provides-Extra: full
Requires-Dist: boto3>=1.37.34; extra == 'full'
Requires-Dist: cohere>=5.15.0; extra == 'full'
Requires-Dist: gitpython>=3.1.44; extra == 'full'
Requires-Dist: google-generativeai>=0.8.4; extra == 'full'
Requires-Dist: httpx>=0.28.1; extra == 'full'
Requires-Dist: huggingface-hub>=0.30.2; extra == 'full'
Requires-Dist: ollama>=0.4.7; extra == 'full'
Requires-Dist: openai>=1.74.0; extra == 'full'
Requires-Dist: voyageai>=0.3.2; extra == 'full'
Provides-Extra: server
Requires-Dist: httpx>=0.28.1; extra == 'server'
